pyadb/__init__.py
pyadb/adb.py
pyadb/device.py
pyadb/exceptions.py
pyt_adb-0.1.0.dist-info/METADATA
pyt_adb-0.1.0.dist-info/WHEEL
pyt_adb-0.1.0.dist-info/top_level.txt
pyt_adb-0.1.0.dist-info/RECORD
