Metadata-Version: 2.4
Name: pyt-adb
Version: 0.1.0
Summary: Thư viện Python để giao tiếp với ADB (Android Debug Bridge)
Project-URL: Homepage, https://github.com/cuongpham2107/pyadb
Project-URL: Documentation, https://developer.android.com/tools/adb
Requires-Python: >=3.11
Requires-Dist: subprocess32; python_version < "3.5"
